{
    "type": "FeatureCollection",
    "name": "currentFires",
    "features": [
        {
            "type": "Feature",
            "properties": {
                "typeFire": "typeFire",
                "time": "time",
                "automaticAlarm": "automaticAlarm",
                "active": true
            },
            "geometry": {
                "type": "Point",
                "coordinates": [
                    8.1234567,
                    56.4321567
                ]
            }
        },
        {
            "type": "Feature",
            "properties": {
                "typeFire": "typeFire",
                "time": "time",
                "automaticAlarm": "automaticAlarm",
                "active": true
            },
            "geometry": {
                "type": "Point",
                "coordinates": [
                    10.1234567,
                    56.2134567
                ]
            }
        },
        {
            "type": "Feature",
            "properties": {
                "typeFire": "typeFire",
                "time": "time",
                "automaticAlarm": "automaticAlarm",
                "active": true
            },
            "geometry": {
                "type": "Point",
                "coordinates": [
                    10,
                    57
                ]
            }
        },
        {
            "type": "Feature",
            "properties": {
                "typeFire": "typeFire",
                "time": "time",
                "automaticAlarm": "automaticAlarm",
                "active": true
            },
            "geometry": {
                "type": "Point",
                "coordinates": [
                    9.9,
                    57
                ]
            }
        },
        {
            "type": "Feature",
            "properties": {
                "typeFire": "BIGFIRE",
                "time": "14:56",
                "automaticAlarm": true,
                "active": true
            },
            "geometry": {
                "type": "Point",
                "coordinates": [
                    57.05016,
                    9.9189
                ]
            }
        },
        {
            "type": "Feature",
            "properties": {
                "typeFire": "BIGFIRE",
                "time": "14:56",
                "automaticAlarm": true,
                "active": true
            },
            "geometry": {
                "type": "Point",
                "coordinates": [
                    9.9189,
                    57.05016
                ]
            }
        },
        {
            "type": "Feature",
            "properties": {
                "typeFire": "BIGFIRE",
                "time": "14:56",
                "automaticAlarm": true,
                "active": true
            },
            "geometry": {
                "type": "Point",
                "coordinates": [
                    9.55815,
                    45.22488
                ]
            }
        }
    ]
}