{
    "type": "FeatureCollection",
    "name": "currentFires",
    "features": [
        {
            "type": "Feature",
            "properties": {
                "typeFire": "typeFire",
                "time": "time",
                "automaticAlarm": "automaticAlarm",
                "active": true
            },
            "geometry": {
                "type": "Point",
                "coordinates": [
                    8.1234567,
                    56.4321567
                ]
            }
        },
        {
            "type": "Feature",
            "properties": {
                "typeFire": "typeFire",
                "time": "time",
                "automaticAlarm": "automaticAlarm",
                "active": true
            },
            "geometry": {
                "type": "Point",
                "coordinates": [
                    9.91,
                    57
                ]
            }
        },
        {
            "type": "Feature",
            "properties": {
                "typeFire": "typeFire",
                "time": "time",
                "automaticAlarm": "automaticAlarm",
                "active": true
            },
            "geometry": {
                "type": "Point",
                "coordinates": [
                    10,
                    57
                ]
            }
        },
        {
            "type": "Feature",
            "properties": {
                "typeFire": "typeFire",
                "time": "time",
                "automaticAlarm": "automaticAlarm",
                "active": true
            },
            "geometry": {
                "type": "Point",
                "coordinates": [
                    9.9,
                    57
                ]
            }
        }
    ]
}
