{
    "type": "FeatureCollection",
    "name": "currentFires",
    "features": [
        {
            "type": "Feature",
            "properties": {
                "typeFire": "Hospital Fire",
                "time": "9:13",
                "automaticAlarm": true,
                "active": true,
                "id": 0,
                "assignedCommanders": [
                    16
                ]
            },
            "geometry": {
                "type": "Point",
                "coordinates": [
                    9.90761,
                    57.03713
                ]
            }
        },
        {
            "type": "Feature",
            "properties": {
                "typeFire": "Big Public Fire",
                "time": "9:14",
                "automaticAlarm": true,
                "active": true,
                "id": 1,
                "assignedCommanders": [
                    23,
                    42
                ]
            },
            "geometry": {
                "type": "Point",
                "coordinates": [
                    9.932237,
                    57.046669
                ]
            }
        },
        {
            "type": "Feature",
            "properties": {
                "typeFire": "Apartment Fire",
                "time": "9:14",
                "automaticAlarm": false,
                "active": true,
                "id": 2,
                "assignedCommanders": [
                    54
                ]
            },
            "geometry": {
                "type": "Point",
                "coordinates": [
                    9.931252,
                    57.047947
                ]
            }
        }
    ]
}